{
    "linePayChannelMap" : {
      "Cash" : true,
      "Wechat" : true,
      "Alipay" : true,
      "PayPay" : true,
      "POS" : true,
      "au_Pay" : true,
      "d_Pay" : false,
      "R_Pay" : true,
      "m_Pay" : true,
      "VISA" : true,
      "JCB" : true,
      "Discover" : true,
      "MASTER" : true,
      "UnionPay" : false,
      "Diners_Club" : true,
      "AMERICAN_EXPRESS" : true
    },
    "languages" : [ "JP", "CH", "EN", "KO" ],
    "machineType" : "SWF1",
    "tableNo" : "",
    "shopCode" : "UGE4RRQR",
    "machineCode" : null,
    "logoImage" : "https://s3.ap-northeast-1.amazonaws.com/smartwe-dev/UGE4RRQR/Eu8lq4zT9q-rmanaUFaxP.png?AWSAccessKeyId=AKIAQCBDBFIFTQ7QHL5V&Expires=1758553200&Signature=Nnnes9cpb1yVRlwpOxzY1x3GIQg%3D",
    "homeImages" : [ "https://s3.ap-northeast-1.amazonaws.com/smartwe-dev/UGE4RRQR/arcmi9Ehrj5BYTMFeOwcY.png?AWSAccessKeyId=AKIAQCBDBFIFTQ7QHL5V&Expires=1758553200&Signature=9OPq2DXVhZo2fGkwqHEBwYmmMOE%3D" ],
    "headerImages" : [ "https://s3.ap-northeast-1.amazonaws.com/smartwe-dev/UGE4RRQR/dGkyjQBgql5LRd9oxEfEy.png?AWSAccessKeyId=AKIAQCBDBFIFTQ7QHL5V&Expires=1758553200&Signature=Kiffz0iyzVkCkE5mp%2FI0IGPq5O8%3D" ],
    "lineup" : false,
    "taxSystem" : true,
    "dynamicCode" : true,
    "actuarial" : true,
    "reimburse" : true
  
}